{
  "carsOnSale": [
    {
      "manu": "BMW",
      "model": "M3",
      "location": "Tbilisi",
      "img": "https://images.cars.com/cldstatic/wp-content/uploads/bmw-m3-competition-2021--01-angle--blue--exterior--front.jpg",
      "custom": 1,
      "fuelType": "Petrol"
    },
    {
      "manu": "BMW",
      "model": "M4",
      "location": "Rustavi",
      "img": "https://smartcdn.gprod.postmedia.digital/driving/wp-content/uploads/2021/11/BMW-M4h.jpg",
      "custom": 0,
      "fuelType": "Petrol"
    },
    {
      "manu": "BMW",
      "model": "M5",
      "location": "Gori",
      "img": "https://media.carsandbids.com/cdn-cgi/image/width=2080,quality=70/da4b9237bacccdf19c0760cab7aec4a8359010b0/photos/rG4lWL2g-0tvpmXYg-f.jpg?t=165844463741",
      "custom": 1,
      "fuelType": "Petrol"
    },
    {
      "manu": "Porsche",
      "model": "911-Carrera",
      "location": "Tbilisi",
      "img": "https://media.ed.edmunds-media.com/porsche/911/2024/oem/2024_porsche_911_coupe_carrera-4_fq_oem_1_1280.jpg",
      "custom": 1,
      "fuelType": "Hybrid"
    },
    {
      "manu": "Mercedes-Benz",
      "model": "C-Class",
      "location": "Kutaisi",
      "img": "https://hips.hearstapps.com/hmg-prod/images/2022-mercedes-benz-c-class-106-1613767205.jpg",
      "custom": 0,
      "fuelType": "Petrol"
    },
    {
      "manu": "Porsche",
      "model": "Cayenne",
      "location": "Batumi",
      "img": "https://www.porschedublin.ie/binary/getasync/15599e51-ec93-4812-9131-203984e867a6/image.jpg?s=6",
      "custom": 1,
      "fuelType": "Hybrid"
    },
    {
      "manu": "Mercedes-Benz",
      "model": "E-Class",
      "location": "Poti",
      "img": "https://cdn.carbuzz.com/gallery-images/1600/1131000/0/1131057.jpg",
      "custom": 0,
      "fuelType": "Electric"
    },
    {
      "manu": "Porsche",
      "model": "Panamera",
      "location": "Rustavi",
      "img": "https://imageio.forbes.com/specials-images/imageserve/6188bd471b02b8e76cb3fa1f/0x0.jpg?format=jpg&width=1200",
      "custom": 1,
      "fuelType": "Hybrid"
    },
    {
      "manu": "Mercedes-Benz",
      "model": "S-Class",
      "location": "Tbilisi",
      "img": "https://stimg.cardekho.com/images/carexteriorimages/930x620/Mercedes-Benz/S-Class/10853/1690451611932/front-left-side-47.jpg",
      "custom": 0,
      "fuelType": "Petrol"
    },
    {
      "manu": "Porsche",
      "model": "Cayman",
      "location": "Kutaisi",
      "img": "https://static01.nyt.com/images/2016/11/22/automobiles/autoreviews/driven-porsche-718/driven-porsche-718-superJumbo.jpg",
      "custom": 1,
      "fuelType": "Hybrid"
    },
    {
      "manu": "Mercedes-Benz",
      "model": "GLE",
      "location": "Batumi",
      "img": "https://media.ed.edmunds-media.com/mercedes-benz/gle-class/2021/oem/2021_mercedes-benz_gle-class_4dr-suv_amg-gle-53_fq_oem_1_1600.jpg",
      "custom": 0,
      "fuelType": "Petrol"
    },
    {
      "manu": "Porsche",
      "model": "Macan",
      "location": "Poti",
      "img": "https://static.autox.com/uploads/2022/01/Porsche-Macan-front-left-corner-profile.jpg",
      "custom": 1,
      "fuelType": "Hybrid"
    },
    {
      "manu": "Mercedes-Benz",
      "model": "GLC",
      "location": "Rustavi",
      "img": "https://www.purosautos.com/wp-content/uploads/2023/07/mercedes-benz.jpg",
      "custom": 0,
      "fuelType": "Petrol"
    }
  ]
}
